{"expireTime":9007200874056070000,"key":"7a60f81b85a26b0638ea2df564f49a06","val":{"name":"IMAGE_PROCESSING","inputPaths":["/Users/owner/Desktop/web_design/tentouya_hp/src/images/fukuwarai/shirotohoshi/shirotohoshi_16.png"],"outputDir":"/Users/owner/Desktop/web_design/tentouya_hp/public/static/9302db44c8985887f49c7046c113f843","args":{"isLazy":false,"operations":[{"outputPath":"2fa99/shirotohoshi_16.webp","args":{"height":25,"width":25,"cropFocus":17,"toFormat":"webp","fit":"cover"}},{"outputPath":"dbc4a/shirotohoshi_16.webp","args":{"height":50,"width":50,"cropFocus":17,"toFormat":"webp","fit":"cover"}},{"outputPath":"d8057/shirotohoshi_16.webp","args":{"height":100,"width":100,"cropFocus":17,"toFormat":"webp","fit":"cover"}}],"pluginOptions":{"base64Width":20,"forceBase64Format":"","useMozJpeg":false,"stripMetadata":true,"lazyImageGeneration":true,"defaultQuality":50,"failOnError":true,"plugins":[]}}}}